clitw.py
clitw-0.0.10.dist-info/entry_points.txt
clitw-0.0.10.dist-info/LICENSE
clitw-0.0.10.dist-info/WHEEL
clitw-0.0.10.dist-info/METADATA
clitw-0.0.10.dist-info/RECORD
