Metadata-Version: 2.1
Name: clitw
Version: 0.0.10
Summary: CUI Twitter Client on Python
Home-page: https://github.com/w40141
License: MIT
Author: Daisuke Oku
Author-email: w.40141@gmail.com
Requires-Python: >=3.9,<4.0
Classifier: Development Status :: 3 - Alpha
Classifier: Environment :: Console
Classifier: License :: OSI Approved :: MIT License
Classifier: Programming Language :: Python :: 3
Classifier: Programming Language :: Python :: 3.9
Requires-Dist: fire (>=0.4.0,<0.5.0)
Requires-Dist: tweepy (>=3.10.0,<4.0.0)
Project-URL: Repository, https://github.com/w40141/clitw
